AllureClient
