Metadata-Version: 2.1
Name: robotframework-AllureClient
Version: 0.0.7.5
Summary: robot framework client to control allure reporting service using rest api
Home-page: https://opensourcetestops.gitlab.io/robotframeworkallureclient/
Author: mahmoud eltohamy
Author-email: mahmoud.mohammed.elhady@gmail.com
License: MIT
Platform: UNKNOWN
